Metadata-Version: 2.1
Name: fuzzy-matcher
Version: 0.1.0
Summary: A super simple MIT licensed fuzzy matching library
Home-page: https://mrbot.ai
Author: Nathan Zylbersztejn
Author-email: human@mrbot.ai
License: MIT
Platform: UNKNOWN
